{"id":"382a25c3-aed8-4d40-834b-c0e8e1d3e625","ruleset":{"name":"standard","version":"cli","settings":{"foodSpawnChance":15,"minimumFood":1,"hazardDamagePerTurn":14,"hazardMap":"","hazardMapAuthor":"","royale":{"shrinkEveryNTurns":25},"squad":{"allowBodyCollisions":false,"sharedElimination":false,"sharedHealth":false,"sharedLength":false}}},"map":"hz_hazard_pits","timeout":900,"source":""}
{"game":{"id":"382a25c3-aed8-4d40-834b-c0e8e1d3e625","ruleset":{"name":"standard","version":"cli","settings":{"foodSpawnChance":15,"minimumFood":1,"hazardDamagePerTurn":14,"hazardMap":"","hazardMapAuthor":"","royale":{"shrinkEveryNTurns":25},"squad":{"allowBodyCollisions":false,"sharedElimination":false,"sharedHealth":false,"sharedLength":false}}},"map":"hz_hazard_pits","timeout":900,"source":""},"turn":0,"board":{"height":11,"width":11,"snakes":[{"id":"945b68d9-90e9-41c5-a7e2-322c4ae5f32f","name":"RahulMCTS","latency":"0","health":100,"body":[{"x":9,"y":9},{"x":9,"y":9},{"x":9,"y":9}],"head":{"x":9,"y":9},"length":3,"shout":"","squad":"","customizations":{"color":"#05FFE6","head":"default","tail":"default"}},{"id":"5da9fc8a-2e98-4329-9907-a2417fc850f8","name":"Vanilla","latency":"0","health":100,"body":[{"x":9,"y":1},{"x":9,"y":1},{"x":9,"y":1}],"head":{"x":9,"y":1},"length":3,"shout":"","squad":"","customizations":{"color":"#808080","head":"default","tail":"default"}}],"food":[{"x":10,"y":8},{"x":10,"y":2},{"x":5,"y":5}],"hazards":[]},"you":{"id":"5da9fc8a-2e98-4329-9907-a2417fc850f8","name":"Vanilla","latency":"0","health":100,"body":[{"x":9,"y":1},{"x":9,"y":1},{"x":9,"y":1}],"head":{"x":9,"y":1},"length":3,"shout":"","squad":"","customizations":{"color":"#808080","head":"default","tail":"default"}}}
{"game":{"id":"382a25c3-aed8-4d40-834b-c0e8e1d3e625","ruleset":{"name":"standard","version":"cli","settings":{"foodSpawnChance":15,"minimumFood":1,"hazardDamagePerTurn":14,"hazardMap":"","hazardMapAuthor":"","royale":{"shrinkEveryNTurns":25},"squad":{"allowBodyCollisions":false,"sharedElimination":false,"sharedHealth":false,"sharedLength":false}}},"map":"hz_hazard_pits","timeout":900,"source":""},"turn":1,"board":{"height":11,"width":11,"snakes":[{"id":"945b68d9-90e9-41c5-a7e2-322c4ae5f32f","name":"RahulMCTS","latency":"192","health":99,"body":[{"x":10,"y":9},{"x":9,"y":9},{"x":9,"y":9}],"head":{"x":10,"y":9},"length":3,"shout":"","squad":"","customizations":{"color":"#05FFE6","head":"default","tail":"default"}},{"id":"5da9fc8a-2e98-4329-9907-a2417fc850f8","name":"Vanilla","latency":"650","health":99,"body":[{"x":9,"y":0},{"x":9,"y":1},{"x":9,"y":1}],"head":{"x":9,"y":0},"length":3,"shout":"","squad":"","customizations":{"color":"#808080","head":"default","tail":"default"}}],"food":[{"x":10,"y":8},{"x":10,"y":2},{"x":5,"y":5}],"hazards":[]},"you":{"id":"5da9fc8a-2e98-4329-9907-a2417fc850f8","name":"Vanilla","latency":"650","health":99,"body":[{"x":9,"y":0},{"x":9,"y":1},{"x":9,"y":1}],"head":{"x":9,"y":0},"length":3,"shout":"","squad":"","customizations":{"color":"#808080","head":"default","tail":"default"}}}
{"game":{"id":"382a25c3-aed8-4d40-834b-c0e8e1d3e625","ruleset":{"name":"standard","version":"cli","settings":{"foodSpawnChance":15,"minimumFood":1,"hazardDamagePerTurn":14,"hazardMap":"","hazardMapAuthor":"","royale":{"shrinkEveryNTurns":25},"squad":{"allowBodyCollisions":false,"sharedElimination":false,"sharedHealth":false,"sharedLength":false}}},"map":"hz_hazard_pits","timeout":900,"source":""},"turn":2,"board":{"height":11,"width":11,"snakes":[{"id":"945b68d9-90e9-41c5-a7e2-322c4ae5f32f","name":"RahulMCTS","latency":"330","health":100,"body":[{"x":10,"y":8},{"x":10,"y":9},{"x":9,"y":9},{"x":9,"y":9}],"head":{"x":10,"y":8},"length":4,"shout":"","squad":"","customizations":{"color":"#05FFE6","head":"default","tail":"default"}},{"id":"5da9fc8a-2e98-4329-9907-a2417fc850f8","name":"Vanilla","latency":"652","health":98,"body":[{"x":10,"y":0},{"x":9,"y":0},{"x":9,"y":1}],"head":{"x":10,"y":0},"length":3,"shout":"","squad":"","customizations":{"color":"#808080","head":"default","tail":"default"}}],"food":[{"x":10,"y":2},{"x":5,"y":5}],"hazards":[]},"you":{"id":"5da9fc8a-2e98-4329-9907-a2417fc850f8","name":"Vanilla","latency":"652","health":98,"body":[{"x":10,"y":0},{"x":9,"y":0},{"x":9,"y":1}],"head":{"x":10,"y":0},"length":3,"shout":"","squad":"","customizations":{"color":"#808080","head":"default","tail":"default"}}}
{"game":{"id":"382a25c3-aed8-4d40-834b-c0e8e1d3e625","ruleset":{"name":"standard","version":"cli","settings":{"foodSpawnChance":15,"minimumFood":1,"hazardDamagePerTurn":14,"hazardMap":"","hazardMapAuthor":"","royale":{"shrinkEveryNTurns":25},"squad":{"allowBodyCollisions":false,"sharedElimination":false,"sharedHealth":false,"sharedLength":false}}},"map":"hz_hazard_pits","timeout":900,"source":""},"turn":3,"board":{"height":11,"width":11,"snakes":[{"id":"945b68d9-90e9-41c5-a7e2-322c4ae5f32f","name":"RahulMCTS","latency":"284","health":99,"body":[{"x":10,"y":7},{"x":10,"y":8},{"x":10,"y":9},{"x":9,"y":9}],"head":{"x":10,"y":7},"length":4,"shout":"","squad":"","customizations":{"color":"#05FFE6","head":"default","tail":"default"}},{"id":"5da9fc8a-2e98-4329-9907-a2417fc850f8","name":"Vanilla","latency":"654","health":97,"body":[{"x":10,"y":1},{"x":10,"y":0},{"x":9,"y":0}],"head":{"x":10,"y":1},"length":3,"shout":"","squad":"","customizations":{"color":"#808080","head":"default","tail":"default"}}],"food":[{"x":10,"y":2},{"x":5,"y":5},{"x":9,"y":6}],"hazards":[]},"you":{"id":"945b68d9-90e9-41c5-a7e2-322c4ae5f32f","name":"RahulMCTS","latency":"284","health":99,"body":[{"x":10,"y":7},{"x":10,"y":8},{"x":10,"y":9},{"x":9,"y":9}],"head":{"x":10,"y":7},"length":4,"shout":"","squad":"","customizations":{"color":"#05FFE6","head":"default","tail":"default"}}}
{"game":{"id":"382a25c3-aed8-4d40-834b-c0e8e1d3e625","ruleset":{"name":"standard","version":"cli","settings":{"foodSpawnChance":15,"minimumFood":1,"hazardDamagePerTurn":14,"hazardMap":"","hazardMapAuthor":"","royale":{"shrinkEveryNTurns":25},"squad":{"allowBodyCollisions":false,"sharedElimination":false,"sharedHealth":false,"sharedLength":false}}},"map":"hz_hazard_pits","timeout":900,"source":""},"turn":4,"board":{"height":11,"width":11,"snakes":[{"id":"945b68d9-90e9-41c5-a7e2-322c4ae5f32f","name":"RahulMCTS","latency":"119","health":98,"body":[{"x":10,"y":6},{"x":10,"y":7},{"x":10,"y":8},{"x":10,"y":9}],"head":{"x":10,"y":6},"length":4,"shout":"","squad":"","customizations":{"color":"#05FFE6","head":"default","tail":"default"}},{"id":"5da9fc8a-2e98-4329-9907-a2417fc850f8","name":"Vanilla","latency":"652","health":100,"body":[{"x":10,"y":2},{"x":10,"y":1},{"x":10,"y":0},{"x":10,"y":0}],"head":{"x":10,"y":2},"length":4,"shout":"","squad":"","customizations":{"color":"#808080","head":"default","tail":"default"}}],"food":[{"x":5,"y":5},{"x":9,"y":6}],"hazards":[]},"you":{"id":"945b68d9-90e9-41c5-a7e2-322c4ae5f32f","name":"RahulMCTS","latency":"119","health":98,"body":[{"x":10,"y":6},{"x":10,"y":7},{"x":10,"y":8},{"x":10,"y":9}],"head":{"x":10,"y":6},"length":4,"shout":"","squad":"","customizations":{"color":"#05FFE6","head":"default","tail":"default"}}}
{"game":{"id":"382a25c3-aed8-4d40-834b-c0e8e1d3e625","ruleset":{"name":"standard","version":"cli","settings":{"foodSpawnChance":15,"minimumFood":1,"hazardDamagePerTurn":14,"hazardMap":"","hazardMapAuthor":"","royale":{"shrinkEveryNTurns":25},"squad":{"allowBodyCollisions":false,"sharedElimination":false,"sharedHealth":false,"sharedLength":false}}},"map":"hz_hazard_pits","timeout":900,"source":""},"turn":5,"board":{"height":11,"width":11,"snakes":[{"id":"945b68d9-90e9-41c5-a7e2-322c4ae5f32f","name":"RahulMCTS","latency":"54","health":100,"body":[{"x":9,"y":6},{"x":10,"y":6},{"x":10,"y":7},{"x":10,"y":8},{"x":10,"y":8}],"head":{"x":9,"y":6},"length":5,"shout":"","squad":"","customizations":{"color":"#05FFE6","head":"default","tail":"default"}},{"id":"5da9fc8a-2e98-4329-9907-a2417fc850f8","name":"Vanilla","latency":"652","health":99,"body":[{"x":10,"y":3},{"x":10,"y":2},{"x":10,"y":1},{"x":10,"y":0}],"head":{"x":10,"y":3},"length":4,"shout":"","squad":"","customizations":{"color":"#808080","head":"default","tail":"default"}}],"food":[{"x":5,"y":5}],"hazards":[]},"you":{"id":"5da9fc8a-2e98-4329-9907-a2417fc850f8","name":"Vanilla","latency":"652","health":99,"body":[{"x":10,"y":3},{"x":10,"y":2},{"x":10,"y":1},{"x":10,"y":0}],"head":{"x":10,"y":3},"length":4,"shout":"","squad":"","customizations":{"color":"#808080","head":"default","tail":"default"}}}
{"game":{"id":"382a25c3-aed8-4d40-834b-c0e8e1d3e625","ruleset":{"name":"standard","version":"cli","settings":{"foodSpawnChance":15,"minimumFood":1,"hazardDamagePerTurn":14,"hazardMap":"","hazardMapAuthor":"","royale":{"shrinkEveryNTurns":25},"squad":{"allowBodyCollisions":false,"sharedElimination":false,"sharedHealth":false,"sharedLength":false}}},"map":"hz_hazard_pits","timeout":900,"source":""},"turn":6,"board":{"height":11,"width":11,"snakes":[{"id":"945b68d9-90e9-41c5-a7e2-322c4ae5f32f","name":"RahulMCTS","latency":"14","health":99,"body":[{"x":9,"y":5},{"x":9,"y":6},{"x":10,"y":6},{"x":10,"y":7},{"x":10,"y":8}],"head":{"x":9,"y":5},"length":5,"shout":"","squad":"","customizations":{"color":"#05FFE6","head":"default","tail":"default"}},{"id":"5da9fc8a-2e98-4329-9907-a2417fc850f8","name":"Vanilla","latency":"652","health":98,"body":[{"x":10,"y":4},{"x":10,"y":3},{"x":10,"y":2},{"x":10,"y":1}],"head":{"x":10,"y":4},"length":4,"shout":"","squad":"","customizations":{"color":"#808080","head":"default","tail":"default"}}],"food":[{"x":5,"y":5}],"hazards":[]},"you":{"id":"5da9fc8a-2e98-4329-9907-a2417fc850f8","name":"Vanilla","latency":"652","health":98,"body":[{"x":10,"y":4},{"x":10,"y":3},{"x":10,"y":2},{"x":10,"y":1}],"head":{"x":10,"y":4},"length":4,"shout":"","squad":"","customizations":{"color":"#808080","head":"default","tail":"default"}}}
{"game":{"id":"382a25c3-aed8-4d40-834b-c0e8e1d3e625","ruleset":{"name":"standard","version":"cli","settings":{"foodSpawnChance":15,"minimumFood":1,"hazardDamagePerTurn":14,"hazardMap":"","hazardMapAuthor":"","royale":{"shrinkEveryNTurns":25},"squad":{"allowBodyCollisions":false,"sharedElimination":false,"sharedHealth":false,"sharedLength":false}}},"map":"hz_hazard_pits","timeout":900,"source":""},"turn":7,"board":{"height":11,"width":11,"snakes":[{"id":"945b68d9-90e9-41c5-a7e2-322c4ae5f32f","name":"RahulMCTS","latency":"10","health":98,"body":[{"x":9,"y":4},{"x":9,"y":5},{"x":9,"y":6},{"x":10,"y":6},{"x":10,"y":7}],"head":{"x":9,"y":4},"length":5,"shout":"","squad":"","customizations":{"color":"#05FFE6","head":"default","tail":"default"}}],"food":[{"x":5,"y":5}],"hazards":[]},"you":{"id":"5da9fc8a-2e98-4329-9907-a2417fc850f8","name":"Vanilla","latency":"652","health":97,"body":[{"x":9,"y":4},{"x":10,"y":4},{"x":10,"y":3},{"x":10,"y":2}],"head":{"x":9,"y":4},"length":4,"shout":"","squad":"","customizations":{"color":"#808080","head":"default","tail":"default"}}}
{"winnerId":"945b68d9-90e9-41c5-a7e2-322c4ae5f32f","winnerName":"RahulMCTS","isDraw":false}
